j2gpp/__init__.py
j2gpp/__main__.py
j2gpp/cli.py
j2gpp/core.py
j2gpp/engine.py
j2gpp/filters.py
j2gpp/globals.py
j2gpp/j2gpp.py
j2gpp/loaders.py
j2gpp/results.py
j2gpp/tests.py
j2gpp/utils.py
j2gpp-3.3.0.dist-info/licenses/LICENSE
j2gpp-3.3.0.dist-info/METADATA
j2gpp-3.3.0.dist-info/WHEEL
j2gpp-3.3.0.dist-info/entry_points.txt
j2gpp-3.3.0.dist-info/top_level.txt
j2gpp-3.3.0.dist-info/RECORD
