Metadata-Version: 2.4
Name: j2gpp
Version: 3.3.0
Summary: A Jinja2-based General Purpose Preprocessor
Author-email: Louis Duret-Robert <louisduret@gmail.com>
License: MIT
Project-URL: Homepage, https://github.com/Louis-DR/j2gpp
Keywords: j2gpp,jinja2,preprocessor
Classifier: Programming Language :: Python :: 3
Classifier: Operating System :: OS Independent
Requires-Python: >=3.8
License-File: LICENSE
Requires-Dist: jinja2
Requires-Dist: ruamel.yaml
Requires-Dist: xmltodict
Requires-Dist: toml
Requires-Dist: configparser
Requires-Dist: hjson
Requires-Dist: colour
Dynamic: license-file
